{
  "users": [
    {
      "id": 1,
      "userName": "King Joel",
      "password": "joel",
      "email": "joel@mondesir.com",
      "name": "Joel Mondesir"
    },
    {
      "id": 2,
      "userName": "Amy The Ace",
      "password": "amy",
      "email": "amy@turpin.com",
      "name": "Amy Turpin"
    },
    {
      "id": 3,
      "userName": "NeilAmos",
      "password": "neil",
      "email": "neil@amos.com",
      "name": "Neil Amos"
    }
  ],
  "userCreatedStations": [
    {
      "name": "Roots Reggae",
      "country": "",
      "image": {
        "url": "https://static.independent.co.uk/s3fs-public/thumbnails/image/2018/11/29/13/bob-marley.jpg?w968h681",
        "thumb": {
          "url": "https://static.independent.co.uk/s3fs-public/thumbnails/image/2018/11/29/13/bob-marley.jpg?w968h681"
        }
      },
      "slug": "Roots Reggae",
      "website": "",
      "twitter": "",
      "facebook": "",
      "total_listeners": 0,
      "categories": [
        {
          "id": "",
          "title": "",
          "description": "",
          "slug": "",
          "ancestry": null
        }
      ],
      "streams": [
        {
          "stream": "",
          "bitrate": "",
          "content_type": "",
          "status": 1,
          "listeners": 0
        }
      ],
      "created_at": "2019-01-21T04:04:40+01:00",
      "updated_at": "2019-01-21T04:04:40+01:00",
      "created_by": "1234",
      "id": 2
    },
    {
      "name": "Jazz Fusion",
      "country": "",
      "image": {
        "url": "https://m.media-amazon.com/images/I/61skEdpJuOL._SS500_.jpg",
        "thumb": {
          "url": "https://m.media-amazon.com/images/I/61skEdpJuOL._SS500_.jpg"
        }
      },
      "slug": "Jazz Fusion",
      "website": "",
      "twitter": "",
      "facebook": "",
      "total_listeners": 0,
      "categories": [
        {
          "id": "",
          "title": "",
          "description": "",
          "slug": "",
          "ancestry": null
        }
      ],
      "streams": [
        {
          "stream": "",
          "bitrate": "",
          "content_type": "",
          "status": 1,
          "listeners": 0
        }
      ],
      "created_at": "2019-01-21T04:04:40+01:00",
      "updated_at": "2019-01-21T04:04:40+01:00",
      "created_by": "1234",
      "id": 3
    },
    {
      "name": "Jibbs Hip Hop",
      "country": "US",
      "image": {
        "url": "https://mdundo.com/media/playlist/149_jHfdaOif_t.jpg",
        "thumb": {
          "url": "https://mdundo.com/media/playlist/149_jHfdaOif_t.jpg"
        }
      },
      "slug": "Jibbs Hip Hop",
      "website": "",
      "twitter": "",
      "facebook": "",
      "total_listeners": 0,
      "categories": [
        {
          "id": "",
          "title": "Rap",
          "description": "",
          "slug": "Rap",
          "ancestry": null
        }
      ],
      "streams": [
        {
          "stream": "",
          "bitrate": "",
          "content_type": "",
          "status": 1,
          "listeners": 0
        }
      ],
      "created_at": "2019-01-21T04:04:40+01:00",
      "updated_at": "2019-01-21T04:04:40+01:00",
      "created_by": "1234",
      "id": 4
    },
    {
      "name": "Big Mouth 99.7",
      "image": "https://i.iheart.com/v3/re/assets/images/5583.png",
      "genre": "Pop",
      "url": "undefined",
      "id": 5
    },
    {
      "name": "Natty Power Radio",
      "country": "Jamaica",
      "image": {
        "url": "https://i3.radionomy.com/radios/400/bc43bc84-1268-43ca-8b12-a7c3408a23a5.jpg",
        "thumb": {
          "url": "https://i3.radionomy.com/radios/400/bc43bc84-1268-43ca-8b12-a7c3408a23a5.jpg"
        }
      },
      "slug": "Natty Power Radio",
      "website": "https://www.nattypowerradio.com/",
      "twitter": "https://twitter.com/nattypowerradio",
      "facebook": "https://www.facebook.com/Nattypowerradio/",
      "total_listeners": 0,
      "categories": [
        {
          "id": "",
          "title": "Rap",
          "description": "24 Hour Caribbean-programmed Internet radio station in the United States",
          "slug": "Rap",
          "ancestry": null
        }
      ],
      "streams": [
        {
          "stream": "https://www.nattypowerradio.com/",
          "bitrate": "",
          "content_type": "",
          "status": 1,
          "listeners": 0
        }
      ],
      "created_at": "2019-01-21T04:04:40+01:00",
      "updated_at": "2019-01-21T04:04:40+01:00",
      "created_by": "1234",
      "id": 6
    },
    {
      "name": "Hits Radio",
      "country": "US",
      "image": {
        "url": "https://hitsradio.com/assets/images/logo-large.png",
        "thumb": {
          "url": "https://hitsradio.com/assets/images/logo-large.png"
        }
      },
      "slug": "Hits Radio",
      "website": "https://hitsradio.com/#/",
      "twitter": "https://twitter.com/nattypowerradio",
      "facebook": "https://www.facebook.com/977radio/",
      "total_listeners": 0,
      "categories": [
        {
          "id": "",
          "title": "Rap",
          "description": "Listen to the hits now",
          "slug": "Rap",
          "ancestry": null
        }
      ],
      "streams": [
        {
          "stream": "",
          "bitrate": "",
          "content_type": "",
          "status": 1,
          "listeners": 0
        }
      ],
      "created_at": "2019-01-21T04:04:40+01:00",
      "updated_at": "2019-01-21T04:04:40+01:00",
      "created_by": "1234",
      "id": 7
    }
  ]
}